cfgv.py
cfgv-3.3.0.dist-info/LICENSE
cfgv-3.3.0.dist-info/METADATA
cfgv-3.3.0.dist-info/WHEEL
cfgv-3.3.0.dist-info/top_level.txt
cfgv-3.3.0.dist-info/RECORD
